{
  "tconstruct:tools/materials_and_you": {
    "criteria": {
      "crafted_book": "2025-06-05 01:11:41 +0000"
    },
    "done": true
  },
  "tconstruct:internal/starting_book": {
    "criteria": {
      "tick": "2025-06-05 01:11:41 +0000"
    },
    "done": true
  },
  "minecraft:story/obtain_armor": {
    "criteria": {
      "iron_chestplate": "2025-06-05 01:15:51 +0000"
    },
    "done": true
  },
  "minecraft:story/iron_tools": {
    "criteria": {
      "iron_pickaxe": "2025-06-05 01:15:59 +0000"
    },
    "done": true
  },
  "toms_storage:unlock_glowstone": {
    "criteria": {
      "inv_changed-glowstone": "2025-06-05 01:11:41 +0000"
    },
    "done": true
  },
  "tconstruct:tools/tinker_tool": {
    "criteria": {
      "crafted_tool": "2025-06-05 01:15:59 +0000"
    },
    "done": true
  },
  "dungeons_arise:wda_root": {
    "criteria": {
      "WDA": "2025-06-05 01:11:41 +0000"
    },
    "done": true
  },
  "tconstruct:tools/material_master": {
    "criteria": {
      "iron": "2025-06-05 01:15:59 +0000"
    },
    "done": false
  },
  "immersive_armors:recipes/misc/heavy": {
    "criteria": {
      "has_item": "2025-06-05 01:13:01 +0000"
    },
    "done": true
  },
  "dungeons_arise:find_bathhouse": {
    "criteria": {
      "location0": "2025-06-05 01:13:33 +0000"
    },
    "done": true
  },
  "minecraft:story/mine_stone": {
    "criteria": {
      "get_stone": "2025-06-05 01:13:00 +0000"
    },
    "done": true
  },
  "ars_nouveau:root": {
    "criteria": {
      "ars_nouveau:worn_notebook": "2025-06-05 01:11:41 +0000"
    },
    "done": true
  },
  "farmersdelight:main/root": {
    "criteria": {
      "seeds": "2025-06-05 01:11:41 +0000"
    },
    "done": true
  },
  "simplyswords:grant_book_on_first_join": {
    "criteria": {
      "tick": "2025-06-05 01:11:41 +0000"
    },
    "done": true
  },
  "what_gecko:what_the_geck": {
    "criteria": {
      "what_the_geck": "2025-06-05 01:11:41 +0000"
    },
    "done": true
  },
  "toms_storage:unlock_dia_pearl": {
    "criteria": {
      "inv_changed-ender_pearl": "2025-06-05 01:11:41 +0000",
      "inv_changed-diamond": "2025-06-05 01:11:41 +0000"
    },
    "done": true
  },
  "toms_storage:unlock_netherite": {
    "criteria": {
      "inv_changed-netherite": "2025-06-05 01:11:41 +0000"
    },
    "done": true
  },
  "mowziesmobs:root": {
    "criteria": {
      "custom_test_name": "2025-06-05 01:11:41 +0000"
    },
    "done": true
  },
  "immersive_armors:recipes/misc/bone": {
    "criteria": {
      "has_item": "2025-06-05 01:13:02 +0000"
    },
    "done": true
  },
  "betterdungeons:root": {
    "criteria": {
      "always": "2025-06-05 01:11:41 +0000"
    },
    "done": true
  },
  "minecraft:adventure/adventuring_time": {
    "criteria": {
      "minecraft:sunflower_plains": "2025-06-05 01:11:42 +0000"
    },
    "done": false
  },
  "ars_nouveau:novice_spell_book": {
    "criteria": {
      "has_novice_spell_book": "2025-06-05 01:16:06 +0000"
    },
    "done": true
  },
  "eeeabsmobs:eeeabsmobs/root": {
    "criteria": {
      "requirement": "2025-06-05 01:11:41 +0000"
    },
    "done": true
  },
  "born_in_chaos_v1:bornin_chaos": {
    "criteria": {
      "bornin_chaos_0": "2025-06-05 01:11:41 +0000"
    },
    "done": true
  },
  "toms_storage:unlock_chest": {
    "criteria": {
      "inv_changed-chest": "2025-06-05 01:11:41 +0000"
    },
    "done": true
  },
  "betterdeserttemples:root": {
    "criteria": {
      "always": "2025-06-05 01:11:41 +0000"
    },
    "done": true
  },
  "tconstruct:smeltery/structure": {
    "criteria": {
      "open_smeltery": "2025-06-05 01:13:53 +0000"
    },
    "done": true
  },
  "tombstone:adventure/root": {
    "criteria": {
      "auto": "2025-06-05 01:11:42 +0000"
    },
    "done": true
  },
  "cataclysm:root": {
    "criteria": {
      "custom_test_name": "2025-06-05 01:11:41 +0000"
    },
    "done": true
  },
  "pfm:grant_book_on_first_join": {
    "criteria": {
      "tick": "2025-06-05 01:11:41 +0000"
    },
    "done": true
  },
  "tconstruct:smeltery/tool_forge": {
    "criteria": {
      "sledge_hammer": "2025-06-05 01:15:59 +0000"
    },
    "done": false
  },
  "DataVersion": 3465
}